yo_fluq/__init__.py
yo_fluq/push_query.py
yo_fluq/query.py
yo_fluq/queryable.py
yo_fluq/_misc/__init__.py
yo_fluq/_misc/file_io.py
yo_fluq/_misc/obj.py
yo_fluq/_misc/ordered_enum.py
yo_fluq/_misc/small_classes.py
yo_fluq/_push_queries/__init__.py
yo_fluq/_push_queries/arch.py
yo_fluq/_push_queries/transformations.py
yo_fluq/_queryable_helpers/__init__.py
yo_fluq/_queryable_helpers/combinatorics.py
yo_fluq/_queryable_helpers/core.py
yo_fluq/_queryable_helpers/extended.py
yo_fluq/_queryable_helpers/files.py
yo_fluq/_queryable_helpers/loop.py
yo_fluq/_queryable_helpers/original_asq_ordering.py
yo_fluq/_queryable_helpers/pandas_df_iter.py
yo_fluq/_queryable_helpers/parallel.py
yo_fluq/agg/__init__.py
yo_fluq/agg/arithmetic.py
yo_fluq/agg/collections.py
yo_fluq/agg/files.py
yo_fluq/agg/pandas_agg.py
yo_fluq/fluq/__init__.py
yo_fluq/fluq/pandas/__init__.py
yo_fluq/fluq/pandas/_add_ordering_column.py
yo_fluq/fluq/pandas/_fractions.py
yo_fluq/fluq/pandas/_stratify.py
yo_fluq/fluq/pandas/_trimmer.py
yo_fluq/fluq/queries/__init__.py
yo_fluq/fluq/queries/_with.py
yo_fluq/fluq/queries/misc.py
yo_fluq/fluq/queries/partition.py
yo_fluq-2.0.7.dist-info/METADATA
yo_fluq-2.0.7.dist-info/WHEEL
yo_fluq-2.0.7.dist-info/top_level.txt
yo_fluq-2.0.7.dist-info/RECORD
