Metadata-Version: 2.1
Name: yo_fluq
Version: 2.0.7
Summary: LINQ port to Python and some smaller useful functional things
Author-email: Yuri Okulovsky <yuri.okulovsky@gmail.com>
